cryptorama/__init__.py
cryptorama/alphabet.py
cryptorama/cipher.py
cryptorama/data.py
cryptorama/message.py
cryptorama/test.py
cryptorama/version.py
cryptorama-0.1.5.dist-info/DESCRIPTION.rst
cryptorama-0.1.5.dist-info/METADATA
cryptorama-0.1.5.dist-info/RECORD
cryptorama-0.1.5.dist-info/WHEEL
cryptorama-0.1.5.dist-info/metadata.json
cryptorama-0.1.5.dist-info/top_level.txt
